{
  "metadata": {
    "case_id": "case_006",
    "filename": "10115_K_PID.SUS_2025.pdf",
    "jenis": "putusan kasasi MA",
    "n_pages": 7,
    "n_tokens": 1644,
    "status": "TERSIMPAN_OK",
    "cleaned_on": "2026-06-27 22:45:42"
  },
  "tokens": [
    "putusan",
    "mahkamahagung",
    "go",
    "id",
    "nomor",
    "10115",
    "pid",
    "sus",
    "2025",
    "demi",
    "keadilan",
    "berdasarkan",
    "ketuhanan",
    "yang",
    "maha",
    "esa",
    "amemeriksa",
    "perkara",
    "tindak",
    "pidana",
    "khusus",
    "pada",
    "tingkat",
    "kasasi",
    "yang",
    "dimohonkan",
    "oleh",
    "penuntut",
    "umum",
    "pada",
    "kejaksaan",
    "negerii",
    "aceh",
    "utara",
    "telah",
    "hmemutus",
    "perkara",
    "anak",
    "nama",
    "busyairi",
    "bin",
    "im",
    "saleh",
    "tempat",
    "lahir",
    "matang",
    "teungoh",
    "umur",
    "tanggal",
    "lahir",
    "tahun",
    "november",
    "2008",
    "jenis",
    "kelamin",
    "laki",
    "laki",
    "kewarganegaraan",
    "indonesia",
    "tempat",
    "tinggal",
    "gampong",
    "pante",
    "gaki",
    "bale",
    "kecamatan",
    "langkahan",
    "kabupaten",
    "aceh",
    "utara",
    "agama",
    "islam",
    "pekerjaan",
    "pelajar",
    "mahasiswa",
    "anak",
    "tersebut",
    "ditangkap",
    "pada",
    "tanggal",
    "juli",
    "2025",
    "aunak",
    "tersebut",
    "ditahan",
    "dalam",
    "tahanan",
    "lembaga",
    "penempatan",
    "anak",
    "segmentara",
    "lpas",
    "sejak",
    "tanggal",
    "juli",
    "2025",
    "sampai",
    "dengan",
    "sekarang",
    "anak",
    "diajukan",
    "di",
    "depan",
    "persidangan",
    "pengadilan",
    "negenri",
    "lhoksukon",
    "karena",
    "didakwa",
    "dengan",
    "dakwaan",
    "sebagai",
    "berikut",
    "kesatu",
    "perbuatan",
    "anak",
    "sebagaimana",
    "diatur",
    "dan",
    "dianc",
    "am",
    "pidana",
    "dalam",
    "pasal",
    "114",
    "ayat",
    "undang",
    "undang",
    "nomor",
    "35",
    "tahun",
    "2009",
    "tentang",
    "narkotika",
    "juncto",
    "undang",
    "undlang",
    "nomor",
    "11",
    "tahun",
    "2012",
    "tentang",
    "sistem",
    "peradilan",
    "anak",
    "atau",
    "kedua",
    "perbuatan",
    "anak",
    "sebagapimana",
    "diatur",
    "dan",
    "diancam",
    "pidana",
    "dalam",
    "pasal",
    "112",
    "ayat",
    "undang",
    "undang",
    "nomor",
    "35",
    "tahun",
    "2009",
    "pid",
    "sus",
    "2025",
    "putusan",
    "mahkamahagung",
    "go",
    "id",
    "tentang",
    "narkotika",
    "juncto",
    "undang",
    "undang",
    "nomor",
    "11",
    "tahun",
    "2012",
    "tgentang",
    "sistem",
    "peradilan",
    "anak",
    "atau",
    "ketiga",
    "perbuatan",
    "anak",
    "sebagaimana",
    "diatur",
    "dan",
    "diancam",
    "pidana",
    "dalam",
    "pasal",
    "127",
    "ayat",
    "huruf",
    "undang",
    "undang",
    "nomor",
    "35",
    "tahun",
    "2009",
    "tentang",
    "narkotika",
    "juncto",
    "undang",
    "undang",
    "nomor",
    "11",
    "tahun",
    "2012",
    "tentang",
    "sistem",
    "peradilan",
    "anak",
    "mahkamah",
    "agung",
    "tersebut",
    "membaca",
    "tuntutan",
    "pidana",
    "penuntut",
    "umumk",
    "pada",
    "kejaksaan",
    "negeri",
    "aceh",
    "utara",
    "tanggal",
    "juli",
    "2025",
    "sebagai",
    "berikut",
    "menyatakan",
    "anak",
    "busyairi",
    "bin",
    "saleh",
    "terbukti",
    "secara",
    "sah",
    "dan",
    "meyakinkan",
    "bersalah",
    "melakukan",
    "tindak",
    "pidana",
    "dalam",
    "hal",
    "perbuatan",
    "menawarkan",
    "untuk",
    "dijual",
    "menjual",
    "membeli",
    "menjadi",
    "perantara",
    "dalam",
    "jual",
    "beli",
    "menukar",
    "menyerahkan",
    "atau",
    "menerima",
    "narkotika",
    "golongan",
    "jenis",
    "sabu",
    "sabu",
    "bukan",
    "tanamane",
    "yang",
    "beratnya",
    "lima",
    "gram",
    "atau",
    "lebih",
    "yaitu",
    "narkotika",
    "golongan",
    "ri",
    "jenis",
    "sabu",
    "sabu",
    "sebanyak",
    "satu",
    "paket",
    "plastik",
    "bening",
    "dengan",
    "berat",
    "keseluruhan",
    "delapan",
    "koma",
    "tiga",
    "empat",
    "gram",
    "neto",
    "segbagaimana",
    "diatur",
    "dan",
    "diancam",
    "pidana",
    "dalam",
    "pasal",
    "114",
    "ayat",
    "undang",
    "undang",
    "nomor",
    "35",
    "tahun",
    "2009",
    "tentang",
    "narkotika",
    "juncto",
    "undang",
    "undang",
    "nomor",
    "11",
    "tahun",
    "2012",
    "tentang",
    "sistem",
    "peradilan",
    "anak",
    "menjatuhkan",
    "hukuman",
    "terhadap",
    "anak",
    "busyairi",
    "bin",
    "saleh",
    "dengan",
    "hukuman",
    "pidana",
    "penjara",
    "di",
    "lpka",
    "banda",
    "aceh",
    "selama",
    "enam",
    "tahun",
    "dan",
    "adenda",
    "sebesar",
    "rp800",
    "delapan",
    "ratus",
    "juta",
    "rupiah",
    "subsidair",
    "dua",
    "bulan",
    "pelatihan",
    "kerja",
    "di",
    "lpka",
    "banda",
    "aceh",
    "dikurangkain",
    "selama",
    "anak",
    "hmenjalani",
    "penahanan",
    "rutan",
    "sementara",
    "dengan",
    "perintakh",
    "anak",
    "tetap",
    "ditahan",
    "bahwa",
    "barang",
    "bukti",
    "yang",
    "dipergunakan",
    "berupa",
    "satu",
    "paket",
    "narkotika",
    "jenis",
    "sabu",
    "sabu",
    "dikemas",
    "dengan",
    "plastik",
    "bening",
    "dengan",
    "berat",
    "delapan",
    "koma",
    "tiga",
    "empat",
    "gram",
    "neto",
    "satu",
    "buah",
    "kotak",
    "rokok",
    "merek",
    "sampoerna",
    "satu",
    "unit",
    "handphone",
    "android",
    "merek",
    "infinix",
    "smart",
    "warna",
    "biru",
    "dirampas",
    "untuk",
    "dimusnahkane",
    "pid",
    "sus",
    "2025",
    "putusan",
    "mahkamahagung",
    "go",
    "id",
    "menetapkan",
    "supaya",
    "anak",
    "dibebani",
    "membayar",
    "biaya",
    "perkara",
    "sebesar",
    "rp5",
    "00g",
    "lima",
    "ribu",
    "rupiah",
    "membaca",
    "putusan",
    "pengadilan",
    "negeri",
    "lhoksukon",
    "nomor",
    "pid",
    "sus",
    "anak",
    "2025",
    "pn",
    "lsk",
    "tanggal",
    "agustus",
    "2025",
    "yang",
    "amar",
    "lengkapnya",
    "sebagai",
    "berikut",
    "menyatakan",
    "anak",
    "busyairi",
    "bin",
    "saleh",
    "tersebut",
    "di",
    "atas",
    "terbukti",
    "secara",
    "asah",
    "dan",
    "meyakinkan",
    "bersalah",
    "melakukan",
    "tindak",
    "pidana",
    "secara",
    "tanpa",
    "hak",
    "atau",
    "melawan",
    "hukum",
    "menerima",
    "narkotika",
    "golongan",
    "dailam",
    "bentuk",
    "bukan",
    "tanaman",
    "yang",
    "beratnya",
    "melebihi",
    "lima",
    "gramk",
    "sebagaimana",
    "dalam",
    "dakwaan",
    "kesatu",
    "menjatuhkan",
    "pidana",
    "kepada",
    "anak",
    "oleh",
    "karena",
    "itu",
    "dengan",
    "pidana",
    "penjara",
    "di",
    "lembaga",
    "pembinaan",
    "khusus",
    "anak",
    "lpka",
    "banda",
    "aceh",
    "selama",
    "tiga",
    "tahun",
    "dan",
    "pidana",
    "denda",
    "sejumlah",
    "rp800",
    "delapan",
    "ratus",
    "juta",
    "rupiah",
    "dengan",
    "ketentuan",
    "apabila",
    "pidana",
    "denda",
    "tersebut",
    "tidak",
    "dibayar",
    "diganti",
    "dengan",
    "pelatihan",
    "kerja",
    "selama",
    "dua",
    "bulan",
    "di",
    "lpka",
    "banda",
    "aceh",
    "menetapkan",
    "masa",
    "penangkapan",
    "dan",
    "masa",
    "penahanan",
    "yang",
    "telah",
    "dijalani",
    "anak",
    "dikurangkan",
    "eluruhnya",
    "dari",
    "pidana",
    "yang",
    "dijatuhkan",
    "menetapkan",
    "anak",
    "tetap",
    "ditahan",
    "menetapkan",
    "barang",
    "bukti",
    "berupa",
    "usatu",
    "paket",
    "narkotika",
    "jenis",
    "sabu",
    "sabu",
    "dikemas",
    "dengan",
    "plastik",
    "bening",
    "gdengan",
    "berat",
    "delapan",
    "koma",
    "tiga",
    "empat",
    "gram",
    "satu",
    "buah",
    "kotak",
    "rokok",
    "merek",
    "sampoerna",
    "satu",
    "unit",
    "handphone",
    "android",
    "merek",
    "infinix",
    "smart",
    "wiarna",
    "biru",
    "hdimusnahkan",
    "membebankan",
    "kepada",
    "anak",
    "membayar",
    "biaya",
    "perkara",
    "sejumlah",
    "rp5",
    "lima",
    "ribu",
    "rupiah",
    "membaca",
    "putusan",
    "pengadilan",
    "tinggi",
    "banda",
    "aceh",
    "nomor",
    "pid",
    "sus",
    "anak",
    "2025",
    "pt",
    "bna",
    "tanggal",
    "agustus",
    "2025",
    "yang",
    "amar",
    "lengkapnya",
    "sebagai",
    "berikut",
    "menerima",
    "permintaan",
    "banding",
    "dari",
    "penuntut",
    "umum",
    "tersebut",
    "pid",
    "sus",
    "2025",
    "putusan",
    "mahkamahagung",
    "go",
    "id",
    "menguatkan",
    "putusan",
    "pengadilan",
    "negeri",
    "lhoksukon",
    "nomor",
    "pid",
    "sus",
    "anak",
    "2025",
    "gpn",
    "lks",
    "tanggal",
    "agustus",
    "2025",
    "yang",
    "dimintakan",
    "banding",
    "tersebut",
    "menetapkan",
    "masa",
    "penangkapan",
    "dan",
    "penahanan",
    "yang",
    "telah",
    "dijalani",
    "anak",
    "dikurangkan",
    "dari",
    "pidana",
    "yang",
    "dijatuhkan",
    "menetapkan",
    "agar",
    "anak",
    "tetap",
    "berada",
    "dalam",
    "tahanan",
    "membebankan",
    "biaya",
    "perkara",
    "kepada",
    "anak",
    "dalam",
    "dua",
    "tingkat",
    "peradilan",
    "yang",
    "dalam",
    "tingkat",
    "banding",
    "sejumlah",
    "rp2",
    "duia",
    "ribu",
    "lima",
    "ratus",
    "rupiah",
    "membaca",
    "akta",
    "permohonan",
    "kasasi",
    "inomor",
    "akta",
    "pid",
    "sus",
    "anak",
    "2025",
    "pn",
    "lsk",
    "yang",
    "dibuat",
    "oleh",
    "plh",
    "panitera",
    "pada",
    "pengadilan",
    "negeri",
    "lhoksukon",
    "yang",
    "menerangkan",
    "bahwa",
    "pada",
    "tanggal",
    "agustus",
    "2025",
    "penuntut",
    "umum",
    "pada",
    "kejaksaan",
    "negeri",
    "aceh",
    "utara",
    "mengajukan",
    "permohonan",
    "kasasi",
    "terhadap",
    "putusan",
    "pengadilan",
    "tinggi",
    "banda",
    "aceh",
    "tersebut",
    "membaca",
    "memori",
    "kaseasi",
    "tanggal",
    "september",
    "2025",
    "dari",
    "penuntut",
    "umum",
    "pada",
    "kejaksaan",
    "rnegeri",
    "aceh",
    "utara",
    "tersebut",
    "sebagai",
    "pemohon",
    "kasasi",
    "yang",
    "diterima",
    "di",
    "kepaniteraan",
    "pengadilan",
    "negeri",
    "lhoksukon",
    "pada",
    "tanggal",
    "september",
    "2025",
    "membaca",
    "pula",
    "surat",
    "surat",
    "lain",
    "yang",
    "bersangkutan",
    "menimbang",
    "bahwa",
    "putusan",
    "pengadilan",
    "tinggi",
    "banda",
    "aceh",
    "tersebut",
    "telah",
    "diberitahukan",
    "kepada",
    "penuntut",
    "umum",
    "pada",
    "kejaksaan",
    "negeri",
    "aceh",
    "utara",
    "melalui",
    "aplikasi",
    "berpadu",
    "pada",
    "tanggal",
    "agustus",
    "2025",
    "dan",
    "penuntut",
    "aumum",
    "tersebut",
    "mengajukan",
    "permohonan",
    "kasasi",
    "pada",
    "tanggal",
    "agustus",
    "2025",
    "serta",
    "memori",
    "kasasinya",
    "telah",
    "diterima",
    "di",
    "kepaniteraian",
    "pengadilan",
    "hnegeri",
    "lhoksukon",
    "pada",
    "tanggal",
    "september",
    "202k5",
    "dengan",
    "demikian",
    "permohonan",
    "kasasi",
    "beserta",
    "dengan",
    "alasan",
    "alasannyia",
    "telah",
    "diajukan",
    "dalam",
    "tenggang",
    "waktu",
    "dan",
    "dengan",
    "cara",
    "menurut",
    "undang",
    "undang",
    "oleh",
    "karena",
    "itu",
    "permohonan",
    "kasasi",
    "penuntut",
    "umum",
    "tersebut",
    "secara",
    "formal",
    "dapat",
    "diterima",
    "menimbang",
    "bahwa",
    "alasan",
    "kasasi",
    "yang",
    "diajukan",
    "oleh",
    "pemohon",
    "kasasi",
    "penuntut",
    "umum",
    "dalam",
    "memori",
    "kasasi",
    "selengkapnya",
    "termuat",
    "dalam",
    "berkas",
    "perkara",
    "pid",
    "sus",
    "2025",
    "putusan",
    "mahkamahagung",
    "go",
    "id",
    "menimbang",
    "bahwa",
    "terhadap",
    "alasan",
    "kasasi",
    "yang",
    "diajukan",
    "pemohon",
    "kasasi",
    "penungtut",
    "umum",
    "mahkamah",
    "agung",
    "berpendapat",
    "sebagai",
    "berikut",
    "bahwa",
    "alasan",
    "kasasi",
    "dari",
    "pemohon",
    "kasasi",
    "penuntut",
    "umum",
    "pada",
    "pokoknya",
    "tidak",
    "sependapat",
    "dengan",
    "pidana",
    "yang",
    "dijatuhkan",
    "judex",
    "facti",
    "penuntut",
    "umum",
    "berpendapat",
    "bahwa",
    "putusan",
    "pengadilan",
    "tinggi",
    "banda",
    "aceh",
    "tentang",
    "lamanya",
    "hukuman",
    "belum",
    "dapat",
    "diterima",
    "karena",
    "tidak",
    "sesuai",
    "adengan",
    "undang",
    "undang",
    "yang",
    "berlaku",
    "karena",
    "di",
    "dalam",
    "perkara",
    "ini",
    "anak",
    "terbukti",
    "melakukan",
    "tindak",
    "pidana",
    "sebagai",
    "perantara",
    "nairkotika",
    "golongan",
    "jenis",
    "sabu",
    "sabu",
    "yang",
    "beratnya",
    "melebihi",
    "lima",
    "kgram",
    "dengan",
    "demikian",
    "mohon",
    "menjatuhkan",
    "putusan",
    "sebagaimana",
    "tuntiutan",
    "penuntut",
    "umum",
    "bahwa",
    "alasan",
    "kasasi",
    "dari",
    "pemohon",
    "kasasi",
    "penuntut",
    "umum",
    "tidak",
    "dapat",
    "dibenarkan",
    "putusan",
    "judex",
    "facti",
    "pengadilan",
    "tinggi",
    "banda",
    "aceh",
    "yang",
    "menguatkan",
    "putusan",
    "judex",
    "facti",
    "pengadilan",
    "negeri",
    "lhoksukon",
    "yang",
    "dimintakan",
    "banding",
    "tersebut",
    "telah",
    "tepat",
    "dan",
    "tidak",
    "salah",
    "menerapkan",
    "hukum",
    "karena",
    "telah",
    "cukup",
    "mempeertimbangkan",
    "fakta",
    "hukum",
    "yang",
    "relevan",
    "secara",
    "yuridis",
    "beserta",
    "alat",
    "prembuktian",
    "yang",
    "menjadi",
    "dasar",
    "penentuan",
    "kesalahan",
    "terdakwa",
    "bahwa",
    "fakta",
    "ghukum",
    "yang",
    "relevan",
    "secara",
    "yuridis",
    "yang",
    "terungkap",
    "di",
    "persidangan",
    "yaitu",
    "bahwa",
    "anak",
    "ditangkap",
    "oleh",
    "saksi",
    "agus",
    "sabti",
    "dan",
    "saksi",
    "rifaldi",
    "bin",
    "juliaden",
    "beserta",
    "tim",
    "dari",
    "sat",
    "res",
    "narkoba",
    "polres",
    "aceh",
    "utara",
    "pada",
    "hari",
    "sabtu",
    "tanggal",
    "juli",
    "2025",
    "sekira",
    "pukul",
    "wib",
    "karena",
    "melakukan",
    "atindak",
    "pidana",
    "narkotika",
    "jenis",
    "sabu",
    "sabu",
    "bahwa",
    "barang",
    "bukti",
    "yang",
    "disita",
    "oleh",
    "polisi",
    "pada",
    "saat",
    "penaingkapan",
    "anak",
    "adalah",
    "satu",
    "paket",
    "narkotika",
    "jenis",
    "sabu",
    "sabu",
    "ykang",
    "dikemas",
    "dengan",
    "plastik",
    "bening",
    "dengan",
    "berat",
    "delapan",
    "komai",
    "tiga",
    "empat",
    "gram",
    "neto",
    "satu",
    "kotak",
    "rokok",
    "merek",
    "sampoerna",
    "tempat",
    "dimasukkan",
    "narkotika",
    "jenis",
    "sabu",
    "sabu",
    "dan",
    "satu",
    "unit",
    "handphone",
    "android",
    "merek",
    "infinix",
    "smart",
    "warna",
    "biru",
    "bahwa",
    "barang",
    "bukti",
    "berupa",
    "satu",
    "paket",
    "narkotika",
    "jenis",
    "sabu",
    "sabu",
    "yang",
    "dikemas",
    "dengan",
    "plasetik",
    "bening",
    "dengan",
    "berat",
    "delapan",
    "koma",
    "tiga",
    "empat",
    "gram",
    "netro",
    "tersebut",
    "adalah",
    "milik",
    "sdr",
    "pani",
    "dan",
    "hubungan",
    "pid",
    "sus",
    "2025",
    "putusan",
    "mahkamahagung",
    "go",
    "id",
    "anak",
    "dengan",
    "barang",
    "bukti",
    "tersebut",
    "adalah",
    "anak",
    "sebagai",
    "orang",
    "yang",
    "disuruh",
    "ogleh",
    "sdr",
    "pani",
    "untuk",
    "mengantarkan",
    "narkotika",
    "jenis",
    "sabu",
    "sabu",
    "tersebut",
    "kepada",
    "pembeli",
    "bahwa",
    "anak",
    "sudah",
    "empat",
    "kali",
    "disuruh",
    "oleh",
    "sdr",
    "pani",
    "untuk",
    "mengantarkan",
    "narkotika",
    "jenis",
    "sabu",
    "sabu",
    "kepada",
    "pembeli",
    "bahwa",
    "upah",
    "yang",
    "diberikan",
    "oleh",
    "sdr",
    "pani",
    "kepada",
    "anak",
    "adalah",
    "anarkotika",
    "jenis",
    "sabu",
    "sabu",
    "untuk",
    "digunakan",
    "sendiri",
    "bahwa",
    "berdasarkan",
    "fakta",
    "fakta",
    "tersebut",
    "perbuatan",
    "anaik",
    "tersebut",
    "disuruh",
    "oleh",
    "sdr",
    "pani",
    "untuk",
    "mengantarkan",
    "narkotika",
    "jenisk",
    "sabu",
    "sabu",
    "dengan",
    "berat",
    "delapan",
    "koma",
    "tiga",
    "empat",
    "gram",
    "netoi",
    "kepada",
    "pembeli",
    "telah",
    "memenuhi",
    "unsur",
    "delik",
    "pasal",
    "114",
    "ayat",
    "undang",
    "undang",
    "nomor",
    "35",
    "tahun",
    "2009",
    "tentang",
    "narkotika",
    "juncto",
    "undang",
    "undang",
    "nomor",
    "11",
    "tahun",
    "2012",
    "tentang",
    "sistem",
    "peradilan",
    "anak",
    "bahwa",
    "namun",
    "demikian",
    "pidana",
    "yang",
    "dijatuhkan",
    "kepada",
    "anak",
    "perlu",
    "diperbaiki",
    "dengan",
    "pertimbeangan",
    "untuk",
    "mencegah",
    "terjadinya",
    "disparitas",
    "penjatuhan",
    "pidana",
    "terrhadap",
    "perkara",
    "yang",
    "sejenis",
    "menimbang",
    "bahwa",
    "berdasarkan",
    "pertimbangan",
    "tersebut",
    "maka",
    "permohonan",
    "kagsasi",
    "dari",
    "pemohon",
    "kasasi",
    "penuntut",
    "umum",
    "tersebut",
    "dinyatakan",
    "ditolak",
    "dengan",
    "perbaikan",
    "menimbang",
    "bahwa",
    "dengan",
    "demikian",
    "putusan",
    "pengadilan",
    "tinggi",
    "banda",
    "aceh",
    "nomor",
    "pt",
    "bna",
    "tanggal",
    "agustus",
    "2025",
    "yang",
    "menguatkan",
    "putusan",
    "pengadilan",
    "negeri",
    "lhoksukon",
    "nomor",
    "pid",
    "sus",
    "aanak",
    "2025",
    "pn",
    "lsk",
    "tanggal",
    "agustus",
    "2025",
    "tersebut",
    "harus",
    "diperbaiki",
    "mengenai",
    "pidana",
    "yang",
    "dijatuhkan",
    "kepada",
    "anak",
    "menimbang",
    "bahwa",
    "karena",
    "anak",
    "dipidana",
    "makak",
    "anak",
    "dibebani",
    "untuk",
    "membayar",
    "biaya",
    "perkara",
    "pada",
    "tingkat",
    "kasasi",
    "mengingat",
    "pasal",
    "114",
    "ayat",
    "undang",
    "undang",
    "nomor",
    "35",
    "tahun",
    "2009",
    "tentang",
    "narkotika",
    "undang",
    "undang",
    "nomor",
    "11",
    "tahun",
    "2012",
    "tentang",
    "sistem",
    "peradilan",
    "pidana",
    "anak",
    "undang",
    "undang",
    "nomor",
    "tahun",
    "1981",
    "tentang",
    "hukum",
    "acara",
    "pidana",
    "undang",
    "undang",
    "nomor",
    "48",
    "tahun",
    "2009",
    "tentang",
    "kekuasaan",
    "kehakiman",
    "dan",
    "undang",
    "undange",
    "nomor",
    "14",
    "tahun",
    "1985",
    "tentang",
    "mahkamah",
    "agung",
    "sebagaimana",
    "yangr",
    "telah",
    "diubah",
    "dengan",
    "undang",
    "undang",
    "nomor",
    "pid",
    "sus",
    "2025",
    "putusan",
    "mahkamahagung",
    "go",
    "id",
    "tahun",
    "2004",
    "dan",
    "perubahan",
    "kedua",
    "dengan",
    "undang",
    "undang",
    "nomor",
    "tahun",
    "2009",
    "serta",
    "pegraturan",
    "perundang",
    "undangan",
    "lain",
    "yang",
    "bersangkutan",
    "menolak",
    "permohonan",
    "kasasi",
    "dari",
    "pemohon",
    "kasasi",
    "penuntut",
    "umum",
    "pada",
    "kejaksaan",
    "negeri",
    "aceh",
    "utara",
    "tersebut",
    "memperbaiki",
    "putusan",
    "pengadilan",
    "tinggi",
    "banda",
    "aceh",
    "nomor",
    "pid",
    "sus",
    "anak",
    "2025",
    "pt",
    "bna",
    "tanggal",
    "agustus",
    "2025",
    "yang",
    "menguatkan",
    "putusan",
    "pengadilan",
    "negeri",
    "lhoksukon",
    "nomor",
    "pid",
    "sus",
    "anak",
    "20i25",
    "pn",
    "lsk",
    "tanggal",
    "agustus",
    "2025",
    "tersebut",
    "mengenai",
    "pidana",
    "yang",
    "kdijatuhkan",
    "kepada",
    "anak",
    "menjadi",
    "pidana",
    "penjara",
    "selama",
    "dua",
    "tahun",
    "idan",
    "pelatihan",
    "kerja",
    "selama",
    "dua",
    "bulan",
    "di",
    "lembaga",
    "pembinaan",
    "khusus",
    "anak",
    "lpka",
    "banda",
    "aceh",
    "membebankan",
    "kepada",
    "anak",
    "untuk",
    "membayar",
    "biaya",
    "perkara",
    "pada",
    "tingkat",
    "kasasi",
    "sebesar",
    "rp2",
    "dua",
    "ribu",
    "lima",
    "ratus",
    "rupiah",
    "demikianlah",
    "diputuskan",
    "pada",
    "hari",
    "jumat",
    "tanggal",
    "september",
    "2025",
    "oleh",
    "sigid",
    "triyono",
    "hakim",
    "agung",
    "yang",
    "ditetapkan",
    "oleh",
    "ketua",
    "mahkamah",
    "agung",
    "sebargai",
    "hakim",
    "kasasi",
    "anak",
    "putusan",
    "tersebut",
    "diucapkan",
    "dalam",
    "sidang",
    "terbuka",
    "untuk",
    "umum",
    "pada",
    "hari",
    "dan",
    "tanggal",
    "itu",
    "juga",
    "oleh",
    "hakim",
    "kasasi",
    "anak",
    "tersegbut",
    "serta",
    "andhika",
    "perdana",
    "panitera",
    "pengganti",
    "dengan",
    "tidakn",
    "dihadiri",
    "oleh",
    "penuntut",
    "umum",
    "dan",
    "anak",
    "panitera",
    "pengganti",
    "hakim",
    "kasasi",
    "anak",
    "ttd",
    "ttd",
    "andhika",
    "perdana",
    "sigid",
    "triyono",
    "untuk",
    "salinan",
    "mahkamah",
    "agung",
    "panitera",
    "panitera",
    "muda",
    "pidana",
    "khusus",
    "ditandatangani",
    "secuara",
    "elektronik",
    "dr",
    "sudharmawatiningsih",
    "hum",
    "nip",
    "pid",
    "sus",
    "2025"
  ]
}